ipa/__init__.py
ipa/_version.py
ipa/data_type/__init__.py
ipa/data_type/_math.py
ipa/data_type/_queue.py
ipa/data_type/base.py
ipa/data_type/config.py
ipa/data_type/container.py
ipa/data_type/echarts.py
ipa/data_type/exception.py
ipa/data_type/handler.py
ipa/data_type/lifecycle.py
ipa/data_type/net.py
ipa/data_type/notice.py
ipa/data_type/page.py
ipa/data_type/point.py
ipa/data_type/spatial.py
ipa/data_type/unitable.py
ipa/decorator/__init__.py
ipa/decorator/exception.py
ipa/util/__init__.py
ipa/util/ctx_util.py
ipa/util/date_util.py
ipa/util/db_util.py
ipa/util/dict_util.py
ipa/util/echarts_util.py
ipa/util/fastapi_util.py
ipa/util/io_util.py
ipa/util/lambda_util.py
ipa/util/math_util.py
ipa/util/network_util.py
ipa/util/num_util.py
ipa/util/obj_util.py
ipa/util/os_util.py
ipa/util/path_util.py
ipa/util/pkg_util.py
ipa/util/pydantic_util.py
ipa/util/simpy_util.py
ipa/util/table_util.py
ipa/util/visual_util.py
ipa/util/websocket_util.py
ipa_python_kit-0.0.7.dist-info/METADATA
ipa_python_kit-0.0.7.dist-info/WHEEL
ipa_python_kit-0.0.7.dist-info/top_level.txt
ipa_python_kit-0.0.7.dist-info/RECORD
