Metadata-Version: 2.4
Name: ipa-python-kit
Version: 0.0.7
Summary: kit for python
Author-email: xdewx <present150608@sina.com>
Keywords: python,kit,lib,util
Requires-Python: >=3.8
Requires-Dist: deprecated>=1.3.1
Requires-Dist: pint>=0.21.1
Requires-Dist: pydantic>=2.10.6
Requires-Dist: pyhumps>=3.8.0
